LICENSE
MANIFEST.in
README.md
README_PY.md
setup.py
version
examples-python/gpio.py
examples-python/pwm.py
gpioc/__init__.py
gpioc/pin.py
gpioc/pwm.py
gpioc.egg-info/PKG-INFO
gpioc.egg-info/SOURCES.txt
gpioc.egg-info/dependency_links.txt
gpioc.egg-info/top_level.txt
gpioc/chips/H616.py
gpioc/chips/__init__.py
libgpio/Makefile
libgpio/board-pin.h
libgpio/board-walnutpi1b-emmc.c
libgpio/board-walnutpi1b.c
libgpio/board-walnutpi2b.c
libgpio/board.c
libgpio/board.h
libgpio/format.py
libgpio/gpio.h
libgpio/pin-num.h
libgpio/pinctrl-sun50i-h616-r.c
libgpio/pinctrl-sun50i-h616.c
libgpio/pinctrl-sun55iw3-r.c
libgpio/pinctrl-sun55iw3.c
libgpio/pinctrl-sunxi.c
libgpio/pinctrl-sunxi.h
libgpio/pinctrl.c
libgpio/pinctrl.h
libgpio/pinctrl_py.c
libgpio/socket.c
libgpio/socket.h
libgpio/softpwm.c
libgpio/softpwm.h
libgpio/softpwm_py.c