Metadata-Version: 2.1
Name: gpioc
Version: 1.5
Summary: A module to control GPIO
Home-page: https://github.com/sc-bin/gpioc
Author: sc-bin
Author-email: 3335447573@qq.com
License: MIT
Platform: manylinux
License-File: LICENSE
